sheetsql/__init__.py
sheetsql/connection.py
sheetsql/exceptions.py
sheetsql/spreadsheet.py
sheetsql/utils.py
sheetsql/worksheet.py
sheet_sql-0.1.0.dist-info/LICENSE
sheet_sql-0.1.0.dist-info/WHEEL
sheet_sql-0.1.0.dist-info/METADATA
sheet_sql-0.1.0.dist-info/RECORD
