Metadata-Version: 2.1
Name: sheet-sql
Version: 0.1.0
Summary: SQL for Google Sheets
Home-page: https://github.com/andyh1203/sheet-sql
Author: Andy Huynh
Author-email: andy.huynh312@gmail.com
Requires-Python: >=3.7,<4.0
Classifier: Programming Language :: Python :: 3
Classifier: Programming Language :: Python :: 3.7
Classifier: Programming Language :: Python :: 3.8
Requires-Dist: gspread (>=3.6.0,<4.0.0)
Requires-Dist: importlib_metadata (>=1.7.0,<2.0.0); python_version < "3.8"
Requires-Dist: regex (>=2020.6.8,<2021.0.0)
Requires-Dist: requests (>=2.24.0,<3.0.0)
Project-URL: Documentation, https://sheet-sql.readthedocs.io
Project-URL: Repository, https://github.com/andyh1203/sheet-sql
